wattmaven_solarnetwork_tools/__init__.py
wattmaven_solarnetwork_tools/py.typed
wattmaven_solarnetwork_tools/core/__init__.py
wattmaven_solarnetwork_tools/core/authentication.py
wattmaven_solarnetwork_tools/core/solarnetwork_client.py
wattmaven_solarnetwork_tools-0.4.0.dist-info/METADATA
wattmaven_solarnetwork_tools-0.4.0.dist-info/WHEEL
wattmaven_solarnetwork_tools-0.4.0.dist-info/licenses/LICENSE
wattmaven_solarnetwork_tools-0.4.0.dist-info/RECORD
